atai_whisper_tool/__init__.py
atai_whisper_tool/cli.py
atai_whisper_tool/parser.py
atai_whisper_tool/whisper-speed.sh
atai_whisper_tool/whisper/__init__.py
atai_whisper_tool/whisper/audio.py
atai_whisper_tool/whisper/decoding.py
atai_whisper_tool/whisper/load_models.py
atai_whisper_tool/whisper/timing.py
atai_whisper_tool/whisper/tokenizer.py
atai_whisper_tool/whisper/torch_whisper.py
atai_whisper_tool/whisper/transcribe.py
atai_whisper_tool/whisper/whisper.py
atai_whisper_tool/whisper/writers.py
atai_whisper_tool/whisper/assets/gpt2.tiktoken
atai_whisper_tool/whisper/assets/mel_filters.npz
atai_whisper_tool/whisper/assets/multilingual.tiktoken
atai_whisper_tool-0.0.7.dist-info/LICENSE
atai_whisper_tool-0.0.7.dist-info/METADATA
atai_whisper_tool-0.0.7.dist-info/WHEEL
atai_whisper_tool-0.0.7.dist-info/entry_points.txt
atai_whisper_tool-0.0.7.dist-info/top_level.txt
atai_whisper_tool-0.0.7.dist-info/RECORD
