Metadata-Version: 2.2
Name: atai-whisper-tool
Version: 0.0.7
Summary: OpenAI Whisper with Apple MPS support
Home-page: https://github.com/AtomGradient/atai-whisper-tool
Author: AtomGradient
Author-email: AtomGradient <alex@atomgradient.com>
License: MIT
Project-URL: Homepage, https://github.com/AtomGradient/atai-whisper-tool
Project-URL: Bug Tracker, https://github.com/AtomGradient/atai-whisper-tool/issues
Keywords: audio,whisper,mps,text-extraction,audio-processing
Classifier: Programming Language :: Python :: 3
Classifier: License :: OSI Approved :: MIT License
Classifier: Operating System :: OS Independent
Requires-Python: >=3.7
License-File: LICENSE
Requires-Dist: mlx>=0.1.1
Requires-Dist: numba
Requires-Dist: numpy
Requires-Dist: torch
Requires-Dist: tqdm
Requires-Dist: more-itertools
Requires-Dist: tiktoken
Requires-Dist: huggingface_hub
Requires-Dist: scipy
Dynamic: author
Dynamic: home-page
Dynamic: requires-python
